{"name": "2020-06-29", "children": [{"ranking": 0.0, "name": "cluster_491", "IPs": ["91.195.241.136"], "cluster_label": "suspicious", "NS": ["ns1.sedoparking.com.", "ns2.sedoparking.com."], "children": [{"name": "Google", "children": [{"type": "suspicious", "name": "googleusa.org", "size": 1}, {"type": "", "name": "cagoogle.com", "size": 1}, {"type": "", "name": "googlekid.com", "size": 1}]}, {"name": "YouTube", "children": [{"type": "", "name": "youtuberepeate.com", "size": 1}, {"type": "", "name": "adultyoutube.com", "size": 1}]}]}, {"ranking": 0.0, "name": "cluster_654", "IPs": ["95.168.169.96"], "cluster_label": "suspicious", "NS": ["ns3.theservercluster.com.", "ns2.theservercluster.com.", "ns1.theservercluster.com."], "children": [{"name": "Google", "children": [{"type": "suspicious", "name": "googlesevilla.com", "size": 1}, {"type": "", "name": "googlemadrid.com", "size": 1}]}]}]}
